cybersentry/__init__.py
cybersentry/core.py
cybersentry-1.4.1.dist-info/LICENSE
cybersentry-1.4.1.dist-info/METADATA
cybersentry-1.4.1.dist-info/WHEEL
cybersentry-1.4.1.dist-info/entry_points.txt
cybersentry-1.4.1.dist-info/top_level.txt
cybersentry-1.4.1.dist-info/RECORD
