Metadata-Version: 2.1
Name: cybersentry
Version: 1.4.1
Summary: Advanced Cybersecurity Intelligence Tool
Home-page: https://github.com/Lxsanto/cybersentry
Author: Luca Lorenzi
Author-email: info@orizon.one
Classifier: Development Status :: 4 - Beta
Classifier: Intended Audience :: Information Technology
Classifier: License :: OSI Approved :: MIT License
Classifier: Operating System :: OS Independent
Classifier: Programming Language :: Python :: 3
Classifier: Programming Language :: Python :: 3.6
Classifier: Programming Language :: Python :: 3.7
Classifier: Programming Language :: Python :: 3.8
Classifier: Programming Language :: Python :: 3.9
Classifier: Topic :: Security
Requires-Python: >=3.6
License-File: LICENSE
Requires-Dist: aiohttp<4.0,>=3.7
Requires-Dist: beautifulsoup4<5.0,>=4.9.3
Requires-Dist: dnspython>=2.0.0
Requires-Dist: colorama>=0.4.0
Requires-Dist: pyOpenSSL>=20.0.0
Requires-Dist: aiodns>=3.0.0
Requires-Dist: tqdm>=4.0.0
Requires-Dist: python-dotenv>=0.19.0
Requires-Dist: asyncio>=3.4.3
Requires-Dist: argparse>=1.4.0
